ben_thermal_pfas/__init__.py
ben_thermal_pfas/formatting.py
ben_thermal_pfas/molecule_structures.py
ben_thermal_pfas/parsers.py
ben_thermal_pfas-0.9.0.dist-info/WHEEL
ben_thermal_pfas-0.9.0.dist-info/entry_points.txt
ben_thermal_pfas-0.9.0.dist-info/METADATA
ben_thermal_pfas-0.9.0.dist-info/RECORD
