Metadata-Version: 2.3
Name: ben-thermal-pfas
Version: 0.9.0
Summary: Add your description here
Author: Ben
Author-email: Ben <bennyp2494@gmail.com>
Requires-Dist: numpy>=2.0.2
Requires-Python: >=3.9
